{"keys": ["", "1127", "1070", "1110", "1113", "1119", "2374", "1154", "1033", "2373", "1178", "1030"], "data": {"1154": {"id": "way/181577337"}, "2374": {"id": "way/243291787"}, "1070": {"id": "way/181577038"}, "1127": {"id": "way/181577177"}, "1110": {"id": "way/181577151"}, "1113": {"id": "way/181577154"}, "1119": {"id": "way/181577162"}, "1033": {"id": "way/181576947"}, "1030": {"id": "way/181576941"}, "1178": {"id": "way/181577410"}, "2373": {"id": "way/243291786"}}, "grid": ["                                                                ", "                                                     !          ", "                                                    !!!         ", "                                                  !!!!!         ", "                                                !!!!!!!!        ", "                                              !!!!!!!!!!!       ", "                                               !!!!!!!!!!       ", "                                               !!!!!!!!!        ", "                                                !!!!!!          ", "                                                !!!!            ", "                                                 !!             ", "                                   ##                           ", "                                 ####                           ", "                              ########                          ", "                            ##########                          ", "                            ##########                       $$ ", "                            ###########                    $$$$ ", "                             ##########                  $$$$$$$", "                             ########                    $$$$$$$", "                             #####                       $$$$$$$", "                              #                           $$$$$$", "                                                          $$$$$$", "                                                           $$$$$", "                                                           $$$$$", "                                                            $$$$", "                                                            $$$$", "                                                             $  ", "                                                                ", "                                                                ", "                                                                ", "                                                              %%", "                                                             %%%", "                                                             %%%", "                                             &                %%", "                                            &&                %%", "                                          &&&&&                %", "                                         &&&&&&&               %", "                                         &&&&&&&                ", "                       '''''            &&&&&&&&&               ", "                       '''''          &&&&&&&&&&&               ", "                       ''''''         &&&&&&&&& ((              ", "                       ''''''          &&&&&&&(((((             ", "                        '''''          &&&&&(((((((             ", "                        '''''           &&((((((((((            ", "                        '''''            (((((((((((            ", "                        '''               (((((((((((           ", "                                          (((((((((((           ", "                                           (((((((((((          ", "                                           (((((((((((          ", "                                            ((((((((            ", "                                            ((((((              ", "                                             (((                ", "                            )))              (                  ", "                         )))))))                                ", "                        ))))))))                                ", "                         )))))))               *                ", "                         ))))))))            ***                ", "                         ))))))))           *****               ", "                          )))))))          ******               ", "                          ))))))))          ******              ", "                          ))))))))          ****             ++ ", "                           ))))))            *             ++++ ", "                           )))                            ++++++", "                                       ,                ++++++++"]}