{"keys": ["", "894", "757"], "data": {"757": {"id": "way/176982944"}, "894": {"id": "way/176983119"}}, "grid": ["                                                                ", "                                                                ", "                                                                ", "                                                                ", "                                                                ", "                                                                ", "                                                                ", "                                                                ", "                                                                ", "                                                                ", "                                                                ", "                                                                ", "                                                                ", "                                                                ", "                                                                ", "                                                                ", "                                                                ", "                                                                ", "                                                                ", "                                                                ", "                                                                ", "                                                                ", "                                              !!!!!!!           ", "                                              !!!!!!!           ", "                                              !!!!!!!           ", "                                              !!!!!!!           ", "                                              !!!!!!!           ", "                                              !!!!!!!           ", "                                                                ", "                                                                ", "                                                                ", "                                                                ", "                                                                ", "                                                                ", "                                                                ", "                                                                ", "                                                                ", "                                                                ", "                                                                ", "                                                                ", "                                                                ", "                                                                ", "                                                                ", "                                                                ", "                                                                ", "                                                                ", "                                                                ", "                                                                ", "                                                                ", "                                                                ", "                                                                ", "                                                                ", "                    #                                           ", "               ######                                           ", "               ######                                           ", "               #######                                          ", "               #######                                          ", "               #######                                          ", "               #######                                          ", "               #######                                          ", "                ######                                          ", "                ###                                             ", "                                                                ", "                                                                "]}