{"keys": ["", "519", "57", "309", "70", "52", "192", "561", "226", "296", "525"], "data": {"309": {"addr_house": "27"}, "561": {"addr_house": "9"}, "57": {"addr_house": "26"}, "52": {"addr_house": ""}, "519": {"addr_house": "25\u0430"}, "525": {"addr_house": "30"}, "70": {"addr_house": ""}, "296": {"addr_house": "8"}, "226": {"addr_house": "28"}, "192": {"addr_house": "11"}}, "grid": ["                                         !!!!!!!! ######        ", "                                     !!!!!!!!!!!! #######       ", "                                   !!!!!!!!!!!!!! #######       ", "                                   !!!!!!!!!!!!!!  ######       ", "                                   !!!!!!!!!!!!!!  ######       ", "                                   !!!!!!!    !!   ######       ", "                                   !!!!!!!         ######       ", "                    $$    $$        !!!            #######      ", "                   $$$$$ $$$$$                     #######      ", "                  $$$$$$ $$$$$$$                    ######      ", "                  $$$$$   $$$$$$$$                  ######      ", "                 $$$$$$$   $$$$$$$                  ######      ", "                 $$$$$$$$  $$$$$$                   ######      ", "                $$$$$$$$$$$$$$$$$                   #######     ", "%               $$$$$ $$$$$$$$$$                    #######     ", "%%             $$$$$   $$$$$$$$$                     ######     ", "%%%%           $$$$$     $$$$$$                  ##########     ", "%%%%%           $$$      $$$$$                #############     ", "%%%%              $     $$$$$$                #############     ", "%%%                     $$$$$                 ##########        ", "  %                      $$$$                 ########          ", "                           $                  ########          ", "                                               #######          ", "                                               #######          ", "                                               #######          ", "                                               #######          ", "                                               ########         ", "                                               ########         ", "                                                #######         ", "                                                #######         ", "                                                #######         ", "                                                ########        ", "                                                ########        ", "&                                               ########        ", "                                                 #######        ", "                                                 #######        ", "                                                 #######        ", "                                                 ########       ", "                                                 ########       ", "                                                 ########       ", "                                                  #######       ", "                                                  #######       ", "                                                  ############# ", "                                                  ############# ", "'                                                 ############# ", "''                                                 #############", "'''                                                #############", "''''                                               ###########  ", "'''''                                              #####        ", "'''''''                                                         ", "''''''''                                                        ", "'''''''''                                                       ", " '''''''''                                                      ", "   '''''''''                                                    ", "    ''''''''(                                                   ", "     ''''''(((                                                  ", "      '''''((((                                                 ", "        ''(((((((                                               ", "         (((((((((            ))                   *            ", "          (((((((((           ))))                ***           ", "            (((((((((        ))))                 ****          ", "             (((((((((        ))                   ****         ", "              (((((((((        )                    ****        ", "                ((((((((+                            ***        "]}